teleop/__init__.py
teleop/cert.pem
teleop/index.html
teleop/key.pem
teleop/assets/teleop-ui.js
teleop/basic/__main__.py
teleop/ros2/__main__.py
teleop/ros2_ik/__main__.py
teleop/utils/__init__.py
teleop/utils/jacobi_robot.py
teleop/utils/jacobi_robot_ros.py
teleop/utils/lite6.urdf
teleop/utils/ros_numpy_tf.py
teleop/utils/transform_limiter.py
teleop/xarm/__main__.py
teleop-0.1.4.dist-info/licenses/LICENSE
teleop-0.1.4.dist-info/METADATA
teleop-0.1.4.dist-info/WHEEL
teleop-0.1.4.dist-info/top_level.txt
teleop-0.1.4.dist-info/RECORD
