Metadata-Version: 2.4
Name: teleop
Version: 0.1.4
Summary: Turns your phone into a robot arm teleoperation device by leveraging the WebXR API
Author-email: Spes Robotics <contact@spes.ai>
License:                                  Apache License
Project-URL: Documentation, https://github.com/SpesRobotics/teleop
Project-URL: Source, https://github.com/SpesRobotics/teleop
Project-URL: Tracker, https://github.com/SpesRobotics/teleop/issues
License-File: LICENSE
Requires-Dist: fastapi
Requires-Dist: uvicorn[standard]
Requires-Dist: numpy
Requires-Dist: transforms3d
Requires-Dist: pytest
Requires-Dist: requests
Requires-Dist: websocket-client
Provides-Extra: utils
Requires-Dist: pin; extra == "utils"
Dynamic: license-file
